{
  "id": "sailimuhu",
  "name": "赛里木湖",
  "aliases": [
    "赛里木湖",
    "大西洋最后一滴眼泪",
    "赛湖"
  ],
  "region": "新疆博尔塔拉州博乐市",
  "peak_elevation": 2073.0,
  "coord_sys": "GCJ-02",
  "seasonality": {
    "cloudsea_months": [
      5,
      6,
      7,
      8,
      9
    ],
    "sunrise_months": [
      5,
      6,
      7,
      8,
      9
    ],
    "sunrise_best": "summer"
  },
  "rules": {
    "min_wind": 0.5,
    "max_wind": 15,
    "rh_threshold": 70
  },
  "viewpoints": [
    {
      "id": "dianjiangtai",
      "name": "点将台",
      "lat": 44.695462,
      "lng": 81.075627,
      "elevation": 2075.0,
      "tags": [
        "sunrise",
        "cloudsea"
      ],
      "note": "经典日出机位",
      "viewing_mode": "valley_fill"
    },
    {
      "id": "songlin",
      "name": "松树头",
      "lat": 44.504828,
      "lng": 81.142012,
      "elevation": 2100.0,
      "tags": [
        "sunrise",
        "cloudsea"
      ],
      "note": "俯瞰赛湖全景",
      "viewing_mode": "valley_fill"
    }
  ],
  "source": "curated",
  "cloud_region": {
    "span_lng": 1.5,
    "span_lat": 1.0
  },
  "local_water": {
    "name": "赛里木湖",
    "surface_elev_m": 2073,
    "nearest_distance_km": 0,
    "source": "高山湖泊，湖面即观景点"
  }
}
